sku_template/__init__.py
sku_template/appid_manager_service.py
sku_template/cli.py
sku_template/client.py
sku_template/config_init.py
sku_template/html_report_generator.py
sku_template/sku_query_framework.py
sku_template/templates/README.md
sku_template/templates/script.js
sku_template/templates/styles.css
sku_template/templates/table_report.html
sku_template/templates/fragments/case_details.html
sku_template/templates/fragments/comparison_row.html
sku_template/templates/fragments/comparison_table.html
sku_template/templates/fragments/status_select.html
sku_template/templates/fragments/summary.html
sku_template-1.0.3.dist-info/licenses/LICENSE
tests/__init__.py
tests/test_client.py
sku_template-1.0.3.dist-info/METADATA
sku_template-1.0.3.dist-info/WHEEL
sku_template-1.0.3.dist-info/entry_points.txt
sku_template-1.0.3.dist-info/top_level.txt
sku_template-1.0.3.dist-info/RECORD
